lmlib/__init__.py
lmlib/polynomial/__init__.py
lmlib/polynomial/poly.py
lmlib/statespace/__init__.py
lmlib/statespace/applications.py
lmlib/statespace/backend.py
lmlib/statespace/cost.py
lmlib/statespace/model.py
lmlib/statespace/recursion/__init__.py
lmlib/statespace/recursion/init.py
lmlib/statespace/recursion/jit.py
lmlib/statespace/recursion/py.py
lmlib/utils/__init__.py
lmlib/utils/beta.py
lmlib/utils/check.py
lmlib/utils/generator.py
lmlib/utils/data/EECG_BASELINE_1CH_10S_FS2400HZ.csv
lmlib/utils/data/EECG_FILT_1CH_10S_FS2400HZ.csv
lmlib/utils/data/EECG_FILT_9CH_10S_FS2400HZ.csv
lmlib/utils/data/SECG3_FILT_HP51_3CH_20S_FS2400HZ.csv
lmlib/utils/data/SECG3_RAW_3CH_20S_FS2400HZ.csv
lmlib-2.1.2.dist-info/METADATA
lmlib-2.1.2.dist-info/WHEEL
lmlib-2.1.2.dist-info/licenses/LICENSE.md
lmlib-2.1.2.dist-info/RECORD
