Metadata-Version: 2.1
Name: lmlib
Version: 2.1.2
Summary: A Model-Based Signal Processing Library Working With Windowed Linear State-Space and Polynomial Signal Models.
Project-URL: Homepage, https://lmlib.ch/
Project-URL: Documentation, https://lmlib.ch/stable/html/
Project-URL: Repository, https://github.com/lmlib/lmlib/
Author: Luca Fleischmann, Christof Baeriswyl'
Author-email: Reto Wildhaber <reto.wildhaber@fhnw.ch>, Frédéric Waldmann <frederic.waldmann@fhnw.ch>
Maintainer-email: Frédéric Waldmann <frederic.waldmann@fhnw.ch>, Reto Wildhaber <reto.wildhaber@fhnw.ch>
License: MIT License
License-File: LICENSE.md
Keywords: ALSSM,based,lmlib,model,processing,signal
Classifier: Development Status :: 5 - Production/Stable
Classifier: Operating System :: OS Independent
Classifier: Programming Language :: Python
Requires-Python: >=3.8
Requires-Dist: matplotlib
Requires-Dist: numpy
Requires-Dist: scipy
Provides-Extra: backend
Requires-Dist: numba; extra == 'backend'
